<?xml version="1.0" encoding="UTF-8"?>
<skin version="6.6.6">
  <author>
    <name>martinrotter</name>
  </author>
  <description>Dark variation of solarized theme.</description>

  <palette>
    <color key="FgInteresting">#acc2c5</color>
    <color key="FgSelectedInteresting">#acc2c5</color>
    <color key="FgNewMessages">#B58900</color>
    <color key="FgSelectedNewMessages">#B58900</color>
    <color key="FgError">#DC322F</color>
    <color key="FgSelectedError">#DC322F</color>
    <color key="FgDisabledFeed">#586e75</color>
    <color key="Allright">#859900</color>
  </palette>

  <forced-styles>Fusion</forced-styles>
  <forced-skin-colors>true</forced-skin-colors>
  
  <style-palette>
    <group id="All">
      <color role="Base">#002b36</color>
      <color role="AlternateBase">#073642</color>
      <color role="ToolTipBase" brush="Dense1Pattern">#586e75</color>
      <color role="Dark">#001f27</color>
      <color role="Midlight">#586e75</color>
      <color role="Mid">#657b83</color>
      <color role="Shadow">#073642</color>
      <color role="Light">#839496</color>
      <color role="Highlight">#d33682</color>

      <color role="Window">#073642</color>
      <color role="Button">#073642</color>

      <color role="Text">#96aaac</color>
      <color role="BrightText">#ffffff</color>
      <color role="HighlightedText">#ffffff</color>
      <color role="PlaceholderText">#586e75</color>
      <color role="ToolTipText">#96aaac</color>
      <color role="ButtonText">#ffffff</color>
      <color role="WindowText">#96aaac</color>
      <color role="Link">#268bd2</color>
      <color role="LinkVisited">#6c71c4</color>

      <color role="NoRole">#073642</color>
    </group>

    <group id="Disabled">
      <color role="Base">#002b36</color>
      <color role="Dark">#001f27</color>
      <color role="Shadow">#073642</color>
      <color role="Text">#586e75</color>
      <color role="ButtonText">#586e75</color>
      <color role="WindowText">#586e75</color>
      <color role="Highlight">#d33682</color>
    </group>
</style-palette>

</skin>